{
  "formtabs":[
    {
      "MIGX_id":122,
      "caption":"Services slave",
      "print_before_tabs":"0",
      "fields":[
        {
          "MIGX_id":401,
          "field":"service_title",
          "caption":"Service",
          "description":"Not editable. Loads automatically. \/ \u041d\u0435 \u0440\u0435\u0434\u0430\u043a\u0442\u0438\u0440\u0443\u0435\u0442\u0441\u044f. \u0417\u0430\u0433\u0440\u0443\u0436\u0430\u0435\u0442\u0441\u044f \u0430\u0432\u0442\u043e\u043c\u0430\u0442\u0438\u0447\u0435\u0441\u043a\u0438.",
          "description_is_code":"0",
          "inputTV":"",
          "inputTVtype":"",
          "validation":"",
          "configs":"",
          "restrictive_condition":"",
          "display":"",
          "sourceFrom":"config",
          "sources":"",
          "inputOptionValues":"",
          "default":"",
          "useDefaultIfEmpty":"0",
          "pos":1
        },
        {
          "MIGX_id":405,
          "field":"activeplanet",
          "caption":"Active Planet",
          "description":"",
          "description_is_code":"0",
          "inputTV":"",
          "inputTVtype":"checkbox",
          "validation":"",
          "configs":"",
          "restrictive_condition":"",
          "display":"",
          "sourceFrom":"config",
          "sources":"",
          "inputOptionValues":"Enable==1",
          "default":"0",
          "useDefaultIfEmpty":"0",
          "pos":2
        },
        {
          "MIGX_id":403,
          "field":"evaluation_migx",
          "caption":"Evaluations",
          "description":"Loads automatically after saving \/ \u0417\u0430\u0433\u0440\u0443\u0436\u0430\u0435\u0442\u0441\u044f \u0430\u0432\u0442\u043e\u043c\u0430\u0442\u0438\u0447\u0435\u0441\u043a\u0438 \u043f\u043e\u0441\u043b\u0435 \u0441\u043e\u0445\u0440\u0430\u043d\u0435\u043d\u0438\u044f",
          "description_is_code":"0",
          "inputTV":"",
          "inputTVtype":"migx",
          "validation":"",
          "configs":"in_evaluationsObj",
          "restrictive_condition":"",
          "display":"",
          "sourceFrom":"config",
          "sources":"",
          "inputOptionValues":"",
          "default":"",
          "useDefaultIfEmpty":"0",
          "pos":3
        },
        {
          "MIGX_id":404,
          "field":"contacts",
          "caption":"Contacts",
          "description":"",
          "description_is_code":"0",
          "inputTV":"",
          "inputTVtype":"textarea",
          "validation":"",
          "configs":"",
          "restrictive_condition":"",
          "display":"",
          "sourceFrom":"config",
          "sources":"",
          "inputOptionValues":"",
          "default":"",
          "useDefaultIfEmpty":"0",
          "pos":4
        },
        {
          "MIGX_id":406,
          "field":"desc_en",
          "caption":"Description",
          "description":"",
          "description_is_code":"0",
          "inputTV":"",
          "inputTVtype":"ace",
          "validation":"",
          "configs":"",
          "restrictive_condition":"",
          "display":"",
          "sourceFrom":"config",
          "sources":"",
          "inputOptionValues":"",
          "default":"",
          "useDefaultIfEmpty":"0",
          "pos":5
        },
        {
          "MIGX_id":402,
          "field":"active",
          "caption":"Activation",
          "description":"",
          "description_is_code":"0",
          "inputTV":"",
          "inputTVtype":"checkbox",
          "validation":"",
          "configs":"",
          "restrictive_condition":"",
          "display":"",
          "sourceFrom":"config",
          "sources":"",
          "inputOptionValues":"Enable==1",
          "default":"0",
          "useDefaultIfEmpty":"0",
          "pos":6
        },
        {
          "MIGX_id":400,
          "field":"service_id",
          "caption":"Service",
          "description":"",
          "description_is_code":"0",
          "inputTV":"",
          "inputTVtype":"listbox",
          "validation":"",
          "configs":{
            "typeAhead":true,
            "typeAheadDelay":250
          },
          "restrictive_condition":"",
          "display":"none",
          "sourceFrom":"config",
          "sources":"",
          "inputOptionValues":"@CHUNK listServices",
          "default":"",
          "useDefaultIfEmpty":"0",
          "pos":7
        }
      ],
      "pos":1
    },
    {
      "MIGX_id":123,
      "caption":"Comment",
      "print_before_tabs":"0",
      "fields":[
        {
          "MIGX_id":409,
          "field":"comment",
          "caption":"Comment",
          "description":"",
          "description_is_code":"0",
          "inputTV":"",
          "inputTVtype":"textarea",
          "validation":"",
          "configs":"",
          "restrictive_condition":"",
          "display":"",
          "sourceFrom":"config",
          "sources":"",
          "inputOptionValues":"",
          "default":"",
          "useDefaultIfEmpty":"0",
          "pos":1
        }
      ],
      "pos":2
    },
    {
      "MIGX_id":124,
      "caption":"DE",
      "print_before_tabs":"0",
      "fields":[
        {
          "MIGX_id":410,
          "field":"desc_de",
          "caption":"Description DE",
          "description":"",
          "description_is_code":"0",
          "inputTV":"",
          "inputTVtype":"ace",
          "validation":"",
          "configs":"",
          "restrictive_condition":"",
          "display":"",
          "sourceFrom":"config",
          "sources":"",
          "inputOptionValues":"",
          "default":"",
          "useDefaultIfEmpty":"0",
          "pos":1
        }
      ],
      "pos":3
    }
  ],
  "contextmenus":"edit_migx",
  "actionbuttons":"",
  "columnbuttons":"",
  "filters":"",
  "extended":{
    "migx_add":"",
    "disable_add_item":1,
    "add_items_directly":"",
    "formcaption":"",
    "update_win_title":"",
    "win_id":"",
    "maxRecords":"",
    "addNewItemAt":"bottom",
    "media_source_id":"",
    "multiple_formtabs":"",
    "multiple_formtabs_label":"",
    "multiple_formtabs_field":"",
    "multiple_formtabs_optionstext":"",
    "multiple_formtabs_optionsvalue":"",
    "actionbuttonsperrow":4,
    "winbuttonslist":"",
    "extrahandlers":"this.handleColumnSwitch",
    "filtersperrow":4,
    "packageName":"",
    "classname":"",
    "task":"",
    "getlistsort":"",
    "getlistsortdir":"",
    "sortconfig":"",
    "gridpagesize":"",
    "use_custom_prefix":"0",
    "prefix":"",
    "grid":"",
    "gridload_mode":1,
    "check_resid":1,
    "check_resid_TV":"",
    "join_alias":"",
    "has_jointable":"yes",
    "getlistwhere":"",
    "joins":"",
    "hooksnippets":"",
    "cmpmaincaption":"",
    "cmptabcaption":"",
    "cmptabdescription":"",
    "cmptabcontroller":"",
    "winbuttons":"",
    "onsubmitsuccess":"",
    "submitparams":""
  },
  "permissions":{
    "apiaccess":"",
    "view":"",
    "list":"",
    "save":"",
    "create":"",
    "remove":"",
    "delete":"",
    "publish":"",
    "unpublish":"",
    "viewdeleted":"",
    "viewunpublished":""
  },
  "fieldpermissions":"",
  "columns":[
    {
      "MIGX_id":1,
      "header":"Service",
      "dataIndex":"service_idrender",
      "width":"",
      "sortable":1,
      "show_in_grid":1,
      "customrenderer":"",
      "renderer":"this.renderChunk",
      "clickaction":"",
      "selectorconfig":"",
      "renderchunktpl":"{'[[+service_id]]' | dbdata : 'cmpObjServices' : 'title_en'}",
      "renderoptions":"",
      "editor":""
    },
    {
      "MIGX_id":4,
      "header":"Prices",
      "dataIndex":"evaluation_migxrender",
      "width":"",
      "sortable":"false",
      "show_in_grid":1,
      "customrenderer":"",
      "renderer":"this.renderChunk",
      "clickaction":"",
      "selectorconfig":"",
      "renderchunktpl":"{'@FILE sportcamps\/model\/migx\/tpl_render.html' | chunk : [\n\t'config' => 'dbr_ObjectServices',\n\t'field' => 'evaluation_migxrender',\n\t'service_id' => '[[+service_id]]',\n\t'evaluation_migx' => '[[+evaluation_migx]]'\n]}",
      "renderoptions":"",
      "editor":""
    },
    {
      "MIGX_id":2,
      "header":"Contacts",
      "dataIndex":"contacts",
      "width":"",
      "sortable":"false",
      "show_in_grid":1,
      "customrenderer":"",
      "renderer":"",
      "clickaction":"",
      "selectorconfig":"",
      "renderchunktpl":"",
      "renderoptions":"",
      "editor":""
    },
    {
      "MIGX_id":5,
      "header":"Active Planet",
      "dataIndex":"activeplanet",
      "width":40,
      "sortable":true,
      "show_in_grid":1,
      "customrenderer":"",
      "renderer":"this.renderSwitchStatusOptions",
      "clickaction":"",
      "selectorconfig":"",
      "renderchunktpl":"",
      "renderoptions":[
        {
          "MIGX_id":1,
          "name":"enable",
          "use_as_fallback":"",
          "value":"",
          "clickaction":"",
          "handler":"",
          "image":"assets\/components\/migx\/style\/images\/cb_empty.png"
        },
        {
          "MIGX_id":2,
          "name":"disable",
          "use_as_fallback":"",
          "value":1,
          "clickaction":"",
          "handler":"",
          "image":"assets\/components\/migx\/style\/images\/cb_ticked.png"
        }
      ],
      "editor":""
    },
    {
      "MIGX_id":3,
      "header":"+ \/ -",
      "dataIndex":"active",
      "width":20,
      "sortable":1,
      "show_in_grid":1,
      "customrenderer":"",
      "renderer":"this.renderSwitchStatusOptions",
      "clickaction":"",
      "selectorconfig":"",
      "renderchunktpl":"",
      "renderoptions":[
        {
          "MIGX_id":1,
          "name":"enable",
          "use_as_fallback":"",
          "value":"",
          "clickaction":"",
          "handler":"",
          "image":"assets\/components\/migx\/style\/images\/cross.png"
        },
        {
          "MIGX_id":2,
          "name":"disable",
          "use_as_fallback":"",
          "value":1,
          "clickaction":"",
          "handler":"",
          "image":"assets\/components\/migx\/style\/images\/tick.png"
        }
      ],
      "editor":""
    }
  ],
  "category":"Camp"
}